CognitiveSDK/__init__.py
CognitiveSDK/core/__init__.py
CognitiveSDK/core/metadata_responder.py
CognitiveSDK/core/orcustrator.py
CognitiveSDK/core/proxy.py
CognitiveSDK/core/publisher.py
CognitiveSDK/core/subscriber.py
CognitiveSDK/core/subscriber_manager.py
CognitiveSDK/core_plus/__init__.py
CognitiveSDK/core_plus/uploader/__init__.py
CognitiveSDK/core_plus/uploader/rabbitmq_manager.py
CognitiveSDK/core_plus/uploader/rabbitmq_publisher.py
CognitiveSDK/core_plus/uploader/uploader_manager.py
CognitiveSDK/devices/__init__.py
CognitiveSDK/devices/device.py
CognitiveSDK/devices/device_manager.py
CognitiveSDK/devices/subdevice.py
CognitiveSDK/devices/middlewares/__init__.py
CognitiveSDK/devices/middlewares/brainflow.py
CognitiveSDK/devices/middlewares/synthetic.py
CognitiveSDK/presets/Muse-2.json
CognitiveSDK/presets/Muse-S.json
CognitiveSDK/presets/OpenBCI-daisy.json
CognitiveSDK/presets/Synthetic.json
CognitiveSDK/presets/__init__.py
CognitiveSDK/utils/__init__.py
CognitiveSDK/utils/helpers.py
CognitiveSDK/utils/logger.py
CognitiveSDK/utils/ports.py
CognitiveSDK/utils/shared_state.py
cognitivesdk_plus-2.0.0.post1.dist-info/METADATA
cognitivesdk_plus-2.0.0.post1.dist-info/WHEEL
cognitivesdk_plus-2.0.0.post1.dist-info/top_level.txt
cognitivesdk_plus-2.0.0.post1.dist-info/RECORD
