Metadata-Version: 2.4
Name: cognitivesdk-plus
Version: 2.0.0.post1
Summary: Cognitive SDK
Author: Turan Abdullah
Author-email: abdullah@habs.ai
Requires-Python: >=3.10
Requires-Dist: loguru
Requires-Dist: zmq==0.0.0
Requires-Dist: pyyaml
Requires-Dist: numpy==2.2.4
Requires-Dist: brainflow==5.16.0
Requires-Dist: httpx==0.28.1
Requires-Dist: pika==1.3.2
Requires-Dist: pandas
Dynamic: author
Dynamic: author-email
Dynamic: requires-dist
Dynamic: requires-python
Dynamic: summary
